pages/__init__.py
pages/admin.py
pages/apps.py
pages/managers.py
pages/models.py
pages/fixtures/initial_pages.json
pages/migrations/0001_initial.py
pages/migrations/0002_auto_20210609_2039.py
pages/migrations/0003_auto_20210621_0847.py
pages/migrations/__init__.py
django_advanced_pages-0.8.6.dist-info/LICENSE
django_advanced_pages-0.8.6.dist-info/METADATA
django_advanced_pages-0.8.6.dist-info/WHEEL
django_advanced_pages-0.8.6.dist-info/top_level.txt
django_advanced_pages-0.8.6.dist-info/RECORD
